did_history/__init__.py
did_history/date_utils.py
did_history/did.py
did_history/format.py
did_history/key.py
did_history/loader.py
did_history/resolver.py
did_history/state.py
did_history/tests/test_key.py
did_history/tests/test_reslover.py
did_history/tests/test_state.py
did_tdw/__init__.py
did_tdw/const.py
did_tdw/history.py
did_tdw/proof.py
did_tdw/provision.py
did_tdw/resolver.py
did_tdw/tests/test_proof.py
did_tdw/tests/test_resolver.py
did_tdw/update.py
did_tdw_jamie_testing-0.1.0.dist-info/LICENSE
did_tdw_jamie_testing-0.1.0.dist-info/METADATA
did_tdw_jamie_testing-0.1.0.dist-info/WHEEL
did_tdw_jamie_testing-0.1.0.dist-info/RECORD
