Metadata-Version: 2.1
Name: did-tdw-jamie-testing
Version: 0.1.0
Summary: This repository includes Python libraries for working with `did:tdw` (Trust DID Web) DID documents and the underlying log format.
License: Apache-2.0
Requires-Python: >=3.10,<4.0
Classifier: License :: OSI Approved :: Apache Software License
Classifier: Programming Language :: Python :: 3
Classifier: Programming Language :: Python :: 3.10
Classifier: Programming Language :: Python :: 3.11
Classifier: Programming Language :: Python :: 3.12
Requires-Dist: aiofiles (>=24.1.0,<25.0.0)
Requires-Dist: aiohttp (>=3.10.5,<4.0.0)
Requires-Dist: aries-askar (>=0.3.2,<0.4.0)
Requires-Dist: base58 (>=2.1.0,<2.2.0)
Requires-Dist: jsoncanon (>=0.2.3,<0.3.0)
Requires-Dist: jsonpatch (>=1.33.0,<2.0.0)
Requires-Dist: multiformats (>=0.3.1,<0.4.0)
